image_processing_jonasbrito92_packcage/__init__.py
image_processing_jonasbrito92_packcage/processing/__init__.py
image_processing_jonasbrito92_packcage/processing/combination.py
image_processing_jonasbrito92_packcage/processing/transformation.py
image_processing_jonasbrito92_packcage/utils/__init__.py
image_processing_jonasbrito92_packcage/utils/io.py
image_processing_jonasbrito92_packcage/utils/plot.py
image_processing_jonasbrito92-0.0.1.dist-info/METADATA
image_processing_jonasbrito92-0.0.1.dist-info/WHEEL
image_processing_jonasbrito92-0.0.1.dist-info/top_level.txt
image_processing_jonasbrito92-0.0.1.dist-info/RECORD
