Metadata-Version: 2.1
Name: image-processing-jonasbrito92
Version: 0.0.1
Summary: Image Processing Package using Skimage
Home-page: https://github.com/jonasbrito92/package-template
Author: Jonas
Requires-Python: >=3.5
Requires-Dist: matplotlib
Requires-Dist: numpy
Requires-Dist: scikit-image
